{"solutions":[{"id":429987,"solverName":"top-seed-11-20","problemId":1,"score":14319281580,"solutionPath":"solutions/top-seed-11-20/1.json","tag":"top-seed-11"},{"id":429623,"solverName":"top-seed-11-19","problemId":1,"score":14311387430,"solutionPath":"solutions/top-seed-11-19/1.json","tag":"top-seed-11"},{"id":429167,"solverName":"top-seed-11-18","problemId":1,"score":14309895220,"solutionPath":"solutions/top-seed-11-18/1.json","tag":"top-seed-11"},{"id":428886,"solverName":"top-seed-11-17","problemId":1,"score":14290499730,"solutionPath":"solutions/top-seed-11-17/1.json","tag":"top-seed-11"},{"id":428511,"solverName":"top-seed-11-16","problemId":1,"score":14281459210,"solutionPath":"solutions/top-seed-11-16/1.json","tag":"top-seed-11"},{"id":429988,"solverName":"top-seed-11-20","problemId":2,"score":14563328940,"solutionPath":"solutions/top-seed-11-20/2.json","tag":"top-seed-11"},{"id":429624,"solverName":"top-seed-11-19","problemId":2,"score":14559994300,"solutionPath":"solutions/top-seed-11-19/2.json","tag":"top-seed-11"},{"id":429168,"solverName":"top-seed-11-18","problemId":2,"score":14559353000,"solutionPath":"solutions/top-seed-11-18/2.json","tag":"top-seed-11"},{"id":428887,"solverName":"top-seed-11-17","problemId":2,"score":14555787060,"solutionPath":"solutions/top-seed-11-17/2.json","tag":"top-seed-11"},{"id":428512,"solverName":"top-seed-11-16","problemId":2,"score":14549793320,"solutionPath":"solutions/top-seed-11-16/2.json","tag":"top-seed-11"},{"id":429989,"solverName":"top-seed-11-20","problemId":8,"score":18416598360,"solutionPath":"solutions/top-seed-11-20/8.json","tag":"top-seed-11"},{"id":429625,"solverName":"top-seed-11-19","problemId":8,"score":18414198870,"solutionPath":"solutions/top-seed-11-19/8.json","tag":"top-seed-11"},{"id":429169,"solverName":"top-seed-11-18","problemId":8,"score":18413285860,"solutionPath":"solutions/top-seed-11-18/8.json","tag":"top-seed-11"},{"id":428513,"solverName":"top-seed-11-16","problemId":8,"score":18412552260,"solutionPath":"solutions/top-seed-11-16/8.json","tag":"top-seed-11"},{"id":428062,"solverName":"top-seed-11-15","problemId":8,"score":18410671510,"solutionPath":"solutions/top-seed-11-15/8.json","tag":"top-seed-11"},{"id":429170,"solverName":"top-seed-11-18","problemId":12,"score":9832788770,"solutionPath":"solutions/top-seed-11-18/12.json","tag":"top-seed-11"},{"id":428889,"solverName":"top-seed-11-17","problemId":12,"score":9832725000,"solutionPath":"solutions/top-seed-11-17/12.json","tag":"top-seed-11"},{"id":427296,"solverName":"top-seed-11-13","problemId":12,"score":9832723530,"solutionPath":"solutions/top-seed-11-13/12.json","tag":"top-seed-11"},{"id":426097,"solverName":"top-seed-11-10","problemId":12,"score":9832652710,"solutionPath":"solutions/top-seed-11-10/12.json","tag":"top-seed-11"},{"id":425729,"solverName":"top-seed-11-9","problemId":12,"score":9831775510,"solutionPath":"solutions/top-seed-11-9/12.json","tag":"top-seed-11"},{"id":429991,"solverName":"top-seed-11-20","problemId":30,"score":4534855460,"solutionPath":"solutions/top-seed-11-20/30.json","tag":"top-seed-11"},{"id":429171,"solverName":"top-seed-11-18","problemId":30,"score":4534852220,"solutionPath":"solutions/top-seed-11-18/30.json","tag":"top-seed-11"},{"id":428890,"solverName":"top-seed-11-17","problemId":30,"score":4534851850,"solutionPath":"solutions/top-seed-11-17/30.json","tag":"top-seed-11"},{"id":428515,"solverName":"top-seed-11-16","problemId":30,"score":4534850790,"solutionPath":"solutions/top-seed-11-16/30.json","tag":"top-seed-11"},{"id":428064,"solverName":"top-seed-11-15","problemId":30,"score":4534825190,"solutionPath":"solutions/top-seed-11-15/30.json","tag":"top-seed-11"}]}