{"solutions":[{"id":406998,"solverName":"random-seed-4-20","problemId":1,"score":14140326710,"solutionPath":"solutions/random-seed-4-20/1.json","tag":"random-seed-4"},{"id":405761,"solverName":"random-seed-4-19","problemId":1,"score":14134202080,"solutionPath":"solutions/random-seed-4-19/1.json","tag":"random-seed-4"},{"id":403813,"solverName":"random-seed-4-18","problemId":1,"score":14129095400,"solutionPath":"solutions/random-seed-4-18/1.json","tag":"random-seed-4"},{"id":402710,"solverName":"random-seed-4-17","problemId":1,"score":14111375130,"solutionPath":"solutions/random-seed-4-17/1.json","tag":"random-seed-4"},{"id":401357,"solverName":"random-seed-4-16","problemId":1,"score":14107953340,"solutionPath":"solutions/random-seed-4-16/1.json","tag":"random-seed-4"},{"id":406999,"solverName":"random-seed-4-20","problemId":2,"score":14385463440,"solutionPath":"solutions/random-seed-4-20/2.json","tag":"random-seed-4"},{"id":405762,"solverName":"random-seed-4-19","problemId":2,"score":14367691630,"solutionPath":"solutions/random-seed-4-19/2.json","tag":"random-seed-4"},{"id":403814,"solverName":"random-seed-4-18","problemId":2,"score":14318039120,"solutionPath":"solutions/random-seed-4-18/2.json","tag":"random-seed-4"},{"id":402711,"solverName":"random-seed-4-17","problemId":2,"score":14286629130,"solutionPath":"solutions/random-seed-4-17/2.json","tag":"random-seed-4"},{"id":401358,"solverName":"random-seed-4-16","problemId":2,"score":14235924990,"solutionPath":"solutions/random-seed-4-16/2.json","tag":"random-seed-4"},{"id":407000,"solverName":"random-seed-4-20","problemId":3,"score":969645690,"solutionPath":"solutions/random-seed-4-20/3.json","tag":"random-seed-4"},{"id":405763,"solverName":"random-seed-4-19","problemId":3,"score":969498900,"solutionPath":"solutions/random-seed-4-19/3.json","tag":"random-seed-4"},{"id":403815,"solverName":"random-seed-4-18","problemId":3,"score":967888370,"solutionPath":"solutions/random-seed-4-18/3.json","tag":"random-seed-4"},{"id":402712,"solverName":"random-seed-4-17","problemId":3,"score":967324940,"solutionPath":"solutions/random-seed-4-17/3.json","tag":"random-seed-4"},{"id":400090,"solverName":"random-seed-4-15","problemId":3,"score":966957680,"solutionPath":"solutions/random-seed-4-15/3.json","tag":"random-seed-4"},{"id":407001,"solverName":"random-seed-4-20","problemId":4,"score":436218510,"solutionPath":"solutions/random-seed-4-20/4.json","tag":"random-seed-4"},{"id":405764,"solverName":"random-seed-4-19","problemId":4,"score":436045280,"solutionPath":"solutions/random-seed-4-19/4.json","tag":"random-seed-4"},{"id":403816,"solverName":"random-seed-4-18","problemId":4,"score":435135480,"solutionPath":"solutions/random-seed-4-18/4.json","tag":"random-seed-4"},{"id":402713,"solverName":"random-seed-4-17","problemId":4,"score":434836210,"solutionPath":"solutions/random-seed-4-17/4.json","tag":"random-seed-4"},{"id":401360,"solverName":"random-seed-4-16","problemId":4,"score":434517200,"solutionPath":"solutions/random-seed-4-16/4.json","tag":"random-seed-4"},{"id":407002,"solverName":"random-seed-4-20","problemId":5,"score":761541230,"solutionPath":"solutions/random-seed-4-20/5.json","tag":"random-seed-4"},{"id":405765,"solverName":"random-seed-4-19","problemId":5,"score":760509960,"solutionPath":"solutions/random-seed-4-19/5.json","tag":"random-seed-4"},{"id":403817,"solverName":"random-seed-4-18","problemId":5,"score":757347100,"solutionPath":"solutions/random-seed-4-18/5.json","tag":"random-seed-4"},{"id":402714,"solverName":"random-seed-4-17","problemId":5,"score":753912800,"solutionPath":"solutions/random-seed-4-17/5.json","tag":"random-seed-4"},{"id":401361,"solverName":"random-seed-4-16","problemId":5,"score":752503640,"solutionPath":"solutions/random-seed-4-16/5.json","tag":"random-seed-4"},{"id":407003,"solverName":"random-seed-4-20","problemId":6,"score":1838981400,"solutionPath":"solutions/random-seed-4-20/6.json","tag":"random-seed-4"},{"id":405766,"solverName":"random-seed-4-19","problemId":6,"score":1838644980,"solutionPath":"solutions/random-seed-4-19/6.json","tag":"random-seed-4"},{"id":403818,"solverName":"random-seed-4-18","problemId":6,"score":1837458930,"solutionPath":"solutions/random-seed-4-18/6.json","tag":"random-seed-4"},{"id":402715,"solverName":"random-seed-4-17","problemId":6,"score":1836855660,"solutionPath":"solutions/random-seed-4-17/6.json","tag":"random-seed-4"},{"id":401362,"solverName":"random-seed-4-16","problemId":6,"score":1835329820,"solutionPath":"solutions/random-seed-4-16/6.json","tag":"random-seed-4"},{"id":407004,"solverName":"random-seed-4-20","problemId":7,"score":1018190470,"solutionPath":"solutions/random-seed-4-20/7.json","tag":"random-seed-4"},{"id":405767,"solverName":"random-seed-4-19","problemId":7,"score":1017846550,"solutionPath":"solutions/random-seed-4-19/7.json","tag":"random-seed-4"},{"id":403819,"solverName":"random-seed-4-18","problemId":7,"score":1016115150,"solutionPath":"solutions/random-seed-4-18/7.json","tag":"random-seed-4"},{"id":402716,"solverName":"random-seed-4-17","problemId":7,"score":1014906970,"solutionPath":"solutions/random-seed-4-17/7.json","tag":"random-seed-4"},{"id":401363,"solverName":"random-seed-4-16","problemId":7,"score":1013760700,"solutionPath":"solutions/random-seed-4-16/7.json","tag":"random-seed-4"},{"id":407005,"solverName":"random-seed-4-20","problemId":8,"score":18504614900,"solutionPath":"solutions/random-seed-4-20/8.json","tag":"random-seed-4"},{"id":405768,"solverName":"random-seed-4-19","problemId":8,"score":18504544890,"solutionPath":"solutions/random-seed-4-19/8.json","tag":"random-seed-4"},{"id":403820,"solverName":"random-seed-4-18","problemId":8,"score":18485414660,"solutionPath":"solutions/random-seed-4-18/8.json","tag":"random-seed-4"},{"id":402717,"solverName":"random-seed-4-17","problemId":8,"score":18484408120,"solutionPath":"solutions/random-seed-4-17/8.json","tag":"random-seed-4"},{"id":400095,"solverName":"random-seed-4-15","problemId":8,"score":18484400880,"solutionPath":"solutions/random-seed-4-15/8.json","tag":"random-seed-4"},{"id":407006,"solverName":"random-seed-4-20","problemId":9,"score":959460990,"solutionPath":"solutions/random-seed-4-20/9.json","tag":"random-seed-4"},{"id":405769,"solverName":"random-seed-4-19","problemId":9,"score":959402530,"solutionPath":"solutions/random-seed-4-19/9.json","tag":"random-seed-4"},{"id":403821,"solverName":"random-seed-4-18","problemId":9,"score":958065170,"solutionPath":"solutions/random-seed-4-18/9.json","tag":"random-seed-4"},{"id":402718,"solverName":"random-seed-4-17","problemId":9,"score":958053210,"solutionPath":"solutions/random-seed-4-17/9.json","tag":"random-seed-4"},{"id":401365,"solverName":"random-seed-4-16","problemId":9,"score":958025040,"solutionPath":"solutions/random-seed-4-16/9.json","tag":"random-seed-4"},{"id":407007,"solverName":"random-seed-4-20","problemId":10,"score":383064610,"solutionPath":"solutions/random-seed-4-20/10.json","tag":"random-seed-4"},{"id":405770,"solverName":"random-seed-4-19","problemId":10,"score":383050300,"solutionPath":"solutions/random-seed-4-19/10.json","tag":"random-seed-4"},{"id":403822,"solverName":"random-seed-4-18","problemId":10,"score":382766620,"solutionPath":"solutions/random-seed-4-18/10.json","tag":"random-seed-4"},{"id":402719,"solverName":"random-seed-4-17","problemId":10,"score":382765020,"solutionPath":"solutions/random-seed-4-17/10.json","tag":"random-seed-4"},{"id":401366,"solverName":"random-seed-4-16","problemId":10,"score":382685130,"solutionPath":"solutions/random-seed-4-16/10.json","tag":"random-seed-4"},{"id":407008,"solverName":"random-seed-4-20","problemId":11,"score":2622324260,"solutionPath":"solutions/random-seed-4-20/11.json","tag":"random-seed-4"},{"id":405771,"solverName":"random-seed-4-19","problemId":11,"score":2622228960,"solutionPath":"solutions/random-seed-4-19/11.json","tag":"random-seed-4"},{"id":403823,"solverName":"random-seed-4-18","problemId":11,"score":2617792200,"solutionPath":"solutions/random-seed-4-18/11.json","tag":"random-seed-4"},{"id":402720,"solverName":"random-seed-4-17","problemId":11,"score":2613925580,"solutionPath":"solutions/random-seed-4-17/11.json","tag":"random-seed-4"},{"id":401367,"solverName":"random-seed-4-16","problemId":11,"score":2613684020,"solutionPath":"solutions/random-seed-4-16/11.json","tag":"random-seed-4"},{"id":405772,"solverName":"random-seed-4-19","problemId":12,"score":9843866030,"solutionPath":"solutions/random-seed-4-19/12.json","tag":"random-seed-4"},{"id":403824,"solverName":"random-seed-4-18","problemId":12,"score":9842736480,"solutionPath":"solutions/random-seed-4-18/12.json","tag":"random-seed-4"},{"id":402721,"solverName":"random-seed-4-17","problemId":12,"score":9842701770,"solutionPath":"solutions/random-seed-4-17/12.json","tag":"random-seed-4"},{"id":400099,"solverName":"random-seed-4-15","problemId":12,"score":9842692480,"solutionPath":"solutions/random-seed-4-15/12.json","tag":"random-seed-4"},{"id":398959,"solverName":"random-seed-4-14","problemId":12,"score":9840921960,"solutionPath":"solutions/random-seed-4-14/12.json","tag":"random-seed-4"},{"id":403825,"solverName":"random-seed-4-18","problemId":13,"score":858509750,"solutionPath":"solutions/random-seed-4-18/13.json","tag":"random-seed-4"},{"id":402722,"solverName":"random-seed-4-17","problemId":13,"score":858509600,"solutionPath":"solutions/random-seed-4-17/13.json","tag":"random-seed-4"},{"id":400100,"solverName":"random-seed-4-15","problemId":13,"score":858509430,"solutionPath":"solutions/random-seed-4-15/13.json","tag":"random-seed-4"},{"id":398960,"solverName":"random-seed-4-14","problemId":13,"score":858210710,"solutionPath":"solutions/random-seed-4-14/13.json","tag":"random-seed-4"},{"id":397988,"solverName":"random-seed-4-13","problemId":13,"score":857867830,"solutionPath":"solutions/random-seed-4-13/13.json","tag":"random-seed-4"},{"id":405774,"solverName":"random-seed-4-19","problemId":14,"score":26654850,"solutionPath":"solutions/random-seed-4-19/14.json","tag":"random-seed-4"},{"id":403826,"solverName":"random-seed-4-18","problemId":14,"score":26651240,"solutionPath":"solutions/random-seed-4-18/14.json","tag":"random-seed-4"},{"id":400101,"solverName":"random-seed-4-15","problemId":14,"score":26651210,"solutionPath":"solutions/random-seed-4-15/14.json","tag":"random-seed-4"},{"id":397017,"solverName":"random-seed-4-12","problemId":14,"score":26643670,"solutionPath":"solutions/random-seed-4-12/14.json","tag":"random-seed-4"},{"id":394983,"solverName":"random-seed-4-10","problemId":14,"score":26630840,"solutionPath":"solutions/random-seed-4-10/14.json","tag":"random-seed-4"},{"id":407012,"solverName":"random-seed-4-20","problemId":15,"score":610280390,"solutionPath":"solutions/random-seed-4-20/15.json","tag":"random-seed-4"},{"id":405775,"solverName":"random-seed-4-19","problemId":15,"score":610279670,"solutionPath":"solutions/random-seed-4-19/15.json","tag":"random-seed-4"},{"id":403827,"solverName":"random-seed-4-18","problemId":15,"score":609971730,"solutionPath":"solutions/random-seed-4-18/15.json","tag":"random-seed-4"},{"id":400102,"solverName":"random-seed-4-15","problemId":15,"score":609969390,"solutionPath":"solutions/random-seed-4-15/15.json","tag":"random-seed-4"},{"id":398962,"solverName":"random-seed-4-14","problemId":15,"score":609879740,"solutionPath":"solutions/random-seed-4-14/15.json","tag":"random-seed-4"},{"id":407013,"solverName":"random-seed-4-20","problemId":16,"score":47952170,"solutionPath":"solutions/random-seed-4-20/16.json","tag":"random-seed-4"},{"id":405776,"solverName":"random-seed-4-19","problemId":16,"score":47930640,"solutionPath":"solutions/random-seed-4-19/16.json","tag":"random-seed-4"},{"id":403828,"solverName":"random-seed-4-18","problemId":16,"score":47854270,"solutionPath":"solutions/random-seed-4-18/16.json","tag":"random-seed-4"},{"id":402725,"solverName":"random-seed-4-17","problemId":16,"score":47848010,"solutionPath":"solutions/random-seed-4-17/16.json","tag":"random-seed-4"},{"id":400103,"solverName":"random-seed-4-15","problemId":16,"score":47840760,"solutionPath":"solutions/random-seed-4-15/16.json","tag":"random-seed-4"},{"id":405777,"solverName":"random-seed-4-19","problemId":17,"score":5842760,"solutionPath":"solutions/random-seed-4-19/17.json","tag":"random-seed-4"},{"id":403829,"solverName":"random-seed-4-18","problemId":17,"score":5828160,"solutionPath":"solutions/random-seed-4-18/17.json","tag":"random-seed-4"},{"id":402726,"solverName":"random-seed-4-17","problemId":17,"score":5814290,"solutionPath":"solutions/random-seed-4-17/17.json","tag":"random-seed-4"},{"id":401373,"solverName":"random-seed-4-16","problemId":17,"score":5806020,"solutionPath":"solutions/random-seed-4-16/17.json","tag":"random-seed-4"},{"id":400104,"solverName":"random-seed-4-15","problemId":17,"score":5803570,"solutionPath":"solutions/random-seed-4-15/17.json","tag":"random-seed-4"},{"id":407015,"solverName":"random-seed-4-20","problemId":20,"score":2102160,"solutionPath":"solutions/random-seed-4-20/20.json","tag":"random-seed-4"},{"id":405778,"solverName":"random-seed-4-19","problemId":20,"score":2101920,"solutionPath":"solutions/random-seed-4-19/20.json","tag":"random-seed-4"},{"id":403830,"solverName":"random-seed-4-18","problemId":20,"score":2077950,"solutionPath":"solutions/random-seed-4-18/20.json","tag":"random-seed-4"},{"id":402727,"solverName":"random-seed-4-17","problemId":20,"score":2062140,"solutionPath":"solutions/random-seed-4-17/20.json","tag":"random-seed-4"},{"id":400105,"solverName":"random-seed-4-15","problemId":20,"score":2044780,"solutionPath":"solutions/random-seed-4-15/20.json","tag":"random-seed-4"},{"id":405779,"solverName":"random-seed-4-19","problemId":21,"score":515670,"solutionPath":"solutions/random-seed-4-19/21.json","tag":"random-seed-4"},{"id":403831,"solverName":"random-seed-4-18","problemId":21,"score":513240,"solutionPath":"solutions/random-seed-4-18/21.json","tag":"random-seed-4"},{"id":402728,"solverName":"random-seed-4-17","problemId":21,"score":513040,"solutionPath":"solutions/random-seed-4-17/21.json","tag":"random-seed-4"},{"id":400106,"solverName":"random-seed-4-15","problemId":21,"score":512770,"solutionPath":"solutions/random-seed-4-15/21.json","tag":"random-seed-4"},{"id":398966,"solverName":"random-seed-4-14","problemId":21,"score":512750,"solutionPath":"solutions/random-seed-4-14/21.json","tag":"random-seed-4"},{"id":407017,"solverName":"random-seed-4-20","problemId":22,"score":482339990,"solutionPath":"solutions/random-seed-4-20/22.json","tag":"random-seed-4"},{"id":405780,"solverName":"random-seed-4-19","problemId":22,"score":482339710,"solutionPath":"solutions/random-seed-4-19/22.json","tag":"random-seed-4"},{"id":403832,"solverName":"random-seed-4-18","problemId":22,"score":482339280,"solutionPath":"solutions/random-seed-4-18/22.json","tag":"random-seed-4"},{"id":400107,"solverName":"random-seed-4-15","problemId":22,"score":482339210,"solutionPath":"solutions/random-seed-4-15/22.json","tag":"random-seed-4"},{"id":398967,"solverName":"random-seed-4-14","problemId":22,"score":482337470,"solutionPath":"solutions/random-seed-4-14/22.json","tag":"random-seed-4"},{"id":405781,"solverName":"random-seed-4-19","problemId":23,"score":335956770,"solutionPath":"solutions/random-seed-4-19/23.json","tag":"random-seed-4"},{"id":402730,"solverName":"random-seed-4-17","problemId":23,"score":335956730,"solutionPath":"solutions/random-seed-4-17/23.json","tag":"random-seed-4"},{"id":400108,"solverName":"random-seed-4-15","problemId":23,"score":335956710,"solutionPath":"solutions/random-seed-4-15/23.json","tag":"random-seed-4"},{"id":394990,"solverName":"random-seed-4-10","problemId":23,"score":335956670,"solutionPath":"solutions/random-seed-4-10/23.json","tag":"random-seed-4"},{"id":394017,"solverName":"random-seed-4-9","problemId":23,"score":335956660,"solutionPath":"solutions/random-seed-4-9/23.json","tag":"random-seed-4"},{"id":405782,"solverName":"random-seed-4-19","problemId":24,"score":563825890,"solutionPath":"solutions/random-seed-4-19/24.json","tag":"random-seed-4"},{"id":403834,"solverName":"random-seed-4-18","problemId":24,"score":563825520,"solutionPath":"solutions/random-seed-4-18/24.json","tag":"random-seed-4"},{"id":402731,"solverName":"random-seed-4-17","problemId":24,"score":563825370,"solutionPath":"solutions/random-seed-4-17/24.json","tag":"random-seed-4"},{"id":400109,"solverName":"random-seed-4-15","problemId":24,"score":563825330,"solutionPath":"solutions/random-seed-4-15/24.json","tag":"random-seed-4"},{"id":398969,"solverName":"random-seed-4-14","problemId":24,"score":563567400,"solutionPath":"solutions/random-seed-4-14/24.json","tag":"random-seed-4"},{"id":405783,"solverName":"random-seed-4-19","problemId":25,"score":2278324990,"solutionPath":"solutions/random-seed-4-19/25.json","tag":"random-seed-4"},{"id":403835,"solverName":"random-seed-4-18","problemId":25,"score":2278321140,"solutionPath":"solutions/random-seed-4-18/25.json","tag":"random-seed-4"},{"id":402732,"solverName":"random-seed-4-17","problemId":25,"score":2278320390,"solutionPath":"solutions/random-seed-4-17/25.json","tag":"random-seed-4"},{"id":400110,"solverName":"random-seed-4-15","problemId":25,"score":2278320020,"solutionPath":"solutions/random-seed-4-15/25.json","tag":"random-seed-4"},{"id":398970,"solverName":"random-seed-4-14","problemId":25,"score":2278292890,"solutionPath":"solutions/random-seed-4-14/25.json","tag":"random-seed-4"},{"id":405784,"solverName":"random-seed-4-19","problemId":26,"score":1293059720,"solutionPath":"solutions/random-seed-4-19/26.json","tag":"random-seed-4"},{"id":403836,"solverName":"random-seed-4-18","problemId":26,"score":1293053530,"solutionPath":"solutions/random-seed-4-18/26.json","tag":"random-seed-4"},{"id":402733,"solverName":"random-seed-4-17","problemId":26,"score":1293053520,"solutionPath":"solutions/random-seed-4-17/26.json","tag":"random-seed-4"},{"id":400111,"solverName":"random-seed-4-15","problemId":26,"score":1293053500,"solutionPath":"solutions/random-seed-4-15/26.json","tag":"random-seed-4"},{"id":398971,"solverName":"random-seed-4-14","problemId":26,"score":1293053150,"solutionPath":"solutions/random-seed-4-14/26.json","tag":"random-seed-4"},{"id":405785,"solverName":"random-seed-4-19","problemId":27,"score":1149724980,"solutionPath":"solutions/random-seed-4-19/27.json","tag":"random-seed-4"},{"id":403837,"solverName":"random-seed-4-18","problemId":27,"score":1149724080,"solutionPath":"solutions/random-seed-4-18/27.json","tag":"random-seed-4"},{"id":402734,"solverName":"random-seed-4-17","problemId":27,"score":1149723210,"solutionPath":"solutions/random-seed-4-17/27.json","tag":"random-seed-4"},{"id":400112,"solverName":"random-seed-4-15","problemId":27,"score":1149723110,"solutionPath":"solutions/random-seed-4-15/27.json","tag":"random-seed-4"},{"id":398972,"solverName":"random-seed-4-14","problemId":27,"score":1149712820,"solutionPath":"solutions/random-seed-4-14/27.json","tag":"random-seed-4"},{"id":405786,"solverName":"random-seed-4-19","problemId":28,"score":1240564440,"solutionPath":"solutions/random-seed-4-19/28.json","tag":"random-seed-4"},{"id":403838,"solverName":"random-seed-4-18","problemId":28,"score":1240562520,"solutionPath":"solutions/random-seed-4-18/28.json","tag":"random-seed-4"},{"id":400113,"solverName":"random-seed-4-15","problemId":28,"score":1240533240,"solutionPath":"solutions/random-seed-4-15/28.json","tag":"random-seed-4"},{"id":398973,"solverName":"random-seed-4-14","problemId":28,"score":1240530260,"solutionPath":"solutions/random-seed-4-14/28.json","tag":"random-seed-4"},{"id":394995,"solverName":"random-seed-4-10","problemId":28,"score":1240530170,"solutionPath":"solutions/random-seed-4-10/28.json","tag":"random-seed-4"},{"id":407024,"solverName":"random-seed-4-20","problemId":29,"score":2839586410,"solutionPath":"solutions/random-seed-4-20/29.json","tag":"random-seed-4"},{"id":405787,"solverName":"random-seed-4-19","problemId":29,"score":2839328530,"solutionPath":"solutions/random-seed-4-19/29.json","tag":"random-seed-4"},{"id":403839,"solverName":"random-seed-4-18","problemId":29,"score":2836216820,"solutionPath":"solutions/random-seed-4-18/29.json","tag":"random-seed-4"},{"id":402736,"solverName":"random-seed-4-17","problemId":29,"score":2836105770,"solutionPath":"solutions/random-seed-4-17/29.json","tag":"random-seed-4"},{"id":401382,"solverName":"random-seed-4-16","problemId":29,"score":2835260920,"solutionPath":"solutions/random-seed-4-16/29.json","tag":"random-seed-4"},{"id":407025,"solverName":"random-seed-4-20","problemId":30,"score":4514722150,"solutionPath":"solutions/random-seed-4-20/30.json","tag":"random-seed-4"},{"id":405788,"solverName":"random-seed-4-19","problemId":30,"score":4514721740,"solutionPath":"solutions/random-seed-4-19/30.json","tag":"random-seed-4"},{"id":403840,"solverName":"random-seed-4-18","problemId":30,"score":4513032290,"solutionPath":"solutions/random-seed-4-18/30.json","tag":"random-seed-4"},{"id":402737,"solverName":"random-seed-4-17","problemId":30,"score":4512502760,"solutionPath":"solutions/random-seed-4-17/30.json","tag":"random-seed-4"},{"id":400115,"solverName":"random-seed-4-15","problemId":30,"score":4512500400,"solutionPath":"solutions/random-seed-4-15/30.json","tag":"random-seed-4"},{"id":407026,"solverName":"random-seed-4-20","problemId":31,"score":1575883890,"solutionPath":"solutions/random-seed-4-20/31.json","tag":"random-seed-4"},{"id":405789,"solverName":"random-seed-4-19","problemId":31,"score":1574424330,"solutionPath":"solutions/random-seed-4-19/31.json","tag":"random-seed-4"},{"id":403841,"solverName":"random-seed-4-18","problemId":31,"score":1569148230,"solutionPath":"solutions/random-seed-4-18/31.json","tag":"random-seed-4"},{"id":402738,"solverName":"random-seed-4-17","problemId":31,"score":1565015550,"solutionPath":"solutions/random-seed-4-17/31.json","tag":"random-seed-4"},{"id":401384,"solverName":"random-seed-4-16","problemId":31,"score":1562208120,"solutionPath":"solutions/random-seed-4-16/31.json","tag":"random-seed-4"},{"id":407027,"solverName":"random-seed-4-20","problemId":32,"score":1106710620,"solutionPath":"solutions/random-seed-4-20/32.json","tag":"random-seed-4"},{"id":405790,"solverName":"random-seed-4-19","problemId":32,"score":1105070560,"solutionPath":"solutions/random-seed-4-19/32.json","tag":"random-seed-4"},{"id":403842,"solverName":"random-seed-4-18","problemId":32,"score":1101924630,"solutionPath":"solutions/random-seed-4-18/32.json","tag":"random-seed-4"},{"id":402739,"solverName":"random-seed-4-17","problemId":32,"score":1099328070,"solutionPath":"solutions/random-seed-4-17/32.json","tag":"random-seed-4"},{"id":401385,"solverName":"random-seed-4-16","problemId":32,"score":1097567020,"solutionPath":"solutions/random-seed-4-16/32.json","tag":"random-seed-4"},{"id":407028,"solverName":"random-seed-4-20","problemId":33,"score":255683770,"solutionPath":"solutions/random-seed-4-20/33.json","tag":"random-seed-4"},{"id":405791,"solverName":"random-seed-4-19","problemId":33,"score":255277080,"solutionPath":"solutions/random-seed-4-19/33.json","tag":"random-seed-4"},{"id":403843,"solverName":"random-seed-4-18","problemId":33,"score":253512860,"solutionPath":"solutions/random-seed-4-18/33.json","tag":"random-seed-4"},{"id":402740,"solverName":"random-seed-4-17","problemId":33,"score":252149280,"solutionPath":"solutions/random-seed-4-17/33.json","tag":"random-seed-4"},{"id":401386,"solverName":"random-seed-4-16","problemId":33,"score":250975680,"solutionPath":"solutions/random-seed-4-16/33.json","tag":"random-seed-4"},{"id":407029,"solverName":"random-seed-4-20","problemId":34,"score":445896120,"solutionPath":"solutions/random-seed-4-20/34.json","tag":"random-seed-4"},{"id":405792,"solverName":"random-seed-4-19","problemId":34,"score":445009790,"solutionPath":"solutions/random-seed-4-19/34.json","tag":"random-seed-4"},{"id":403844,"solverName":"random-seed-4-18","problemId":34,"score":442927450,"solutionPath":"solutions/random-seed-4-18/34.json","tag":"random-seed-4"},{"id":402741,"solverName":"random-seed-4-17","problemId":34,"score":441980150,"solutionPath":"solutions/random-seed-4-17/34.json","tag":"random-seed-4"},{"id":401387,"solverName":"random-seed-4-16","problemId":34,"score":441541790,"solutionPath":"solutions/random-seed-4-16/34.json","tag":"random-seed-4"},{"id":407030,"solverName":"random-seed-4-20","problemId":35,"score":550808860,"solutionPath":"solutions/random-seed-4-20/35.json","tag":"random-seed-4"},{"id":405793,"solverName":"random-seed-4-19","problemId":35,"score":550725080,"solutionPath":"solutions/random-seed-4-19/35.json","tag":"random-seed-4"},{"id":403845,"solverName":"random-seed-4-18","problemId":35,"score":549005560,"solutionPath":"solutions/random-seed-4-18/35.json","tag":"random-seed-4"},{"id":402742,"solverName":"random-seed-4-17","problemId":35,"score":548347170,"solutionPath":"solutions/random-seed-4-17/35.json","tag":"random-seed-4"},{"id":401388,"solverName":"random-seed-4-16","problemId":35,"score":547092130,"solutionPath":"solutions/random-seed-4-16/35.json","tag":"random-seed-4"},{"id":407031,"solverName":"random-seed-4-20","problemId":36,"score":442168870,"solutionPath":"solutions/random-seed-4-20/36.json","tag":"random-seed-4"},{"id":405794,"solverName":"random-seed-4-19","problemId":36,"score":442168560,"solutionPath":"solutions/random-seed-4-19/36.json","tag":"random-seed-4"},{"id":403846,"solverName":"random-seed-4-18","problemId":36,"score":441518320,"solutionPath":"solutions/random-seed-4-18/36.json","tag":"random-seed-4"},{"id":402743,"solverName":"random-seed-4-17","problemId":36,"score":441516270,"solutionPath":"solutions/random-seed-4-17/36.json","tag":"random-seed-4"},{"id":401389,"solverName":"random-seed-4-16","problemId":36,"score":441444520,"solutionPath":"solutions/random-seed-4-16/36.json","tag":"random-seed-4"},{"id":407032,"solverName":"random-seed-4-20","problemId":37,"score":1197744560,"solutionPath":"solutions/random-seed-4-20/37.json","tag":"random-seed-4"},{"id":405795,"solverName":"random-seed-4-19","problemId":37,"score":1197734060,"solutionPath":"solutions/random-seed-4-19/37.json","tag":"random-seed-4"},{"id":403847,"solverName":"random-seed-4-18","problemId":37,"score":1196111640,"solutionPath":"solutions/random-seed-4-18/37.json","tag":"random-seed-4"},{"id":402744,"solverName":"random-seed-4-17","problemId":37,"score":1195784160,"solutionPath":"solutions/random-seed-4-17/37.json","tag":"random-seed-4"},{"id":401390,"solverName":"random-seed-4-16","problemId":37,"score":1194214790,"solutionPath":"solutions/random-seed-4-16/37.json","tag":"random-seed-4"},{"id":407033,"solverName":"random-seed-4-20","problemId":38,"score":110923680,"solutionPath":"solutions/random-seed-4-20/38.json","tag":"random-seed-4"},{"id":405796,"solverName":"random-seed-4-19","problemId":38,"score":110843690,"solutionPath":"solutions/random-seed-4-19/38.json","tag":"random-seed-4"},{"id":403848,"solverName":"random-seed-4-18","problemId":38,"score":110689180,"solutionPath":"solutions/random-seed-4-18/38.json","tag":"random-seed-4"},{"id":402745,"solverName":"random-seed-4-17","problemId":38,"score":110663880,"solutionPath":"solutions/random-seed-4-17/38.json","tag":"random-seed-4"},{"id":401391,"solverName":"random-seed-4-16","problemId":38,"score":110656530,"solutionPath":"solutions/random-seed-4-16/38.json","tag":"random-seed-4"},{"id":405797,"solverName":"random-seed-4-19","problemId":39,"score":282873740,"solutionPath":"solutions/random-seed-4-19/39.json","tag":"random-seed-4"},{"id":403849,"solverName":"random-seed-4-18","problemId":39,"score":282692730,"solutionPath":"solutions/random-seed-4-18/39.json","tag":"random-seed-4"},{"id":402746,"solverName":"random-seed-4-17","problemId":39,"score":282671950,"solutionPath":"solutions/random-seed-4-17/39.json","tag":"random-seed-4"},{"id":401392,"solverName":"random-seed-4-16","problemId":39,"score":282671860,"solutionPath":"solutions/random-seed-4-16/39.json","tag":"random-seed-4"},{"id":400124,"solverName":"random-seed-4-15","problemId":39,"score":282671750,"solutionPath":"solutions/random-seed-4-15/39.json","tag":"random-seed-4"},{"id":405798,"solverName":"random-seed-4-19","problemId":40,"score":323747070,"solutionPath":"solutions/random-seed-4-19/40.json","tag":"random-seed-4"},{"id":403850,"solverName":"random-seed-4-18","problemId":40,"score":322959740,"solutionPath":"solutions/random-seed-4-18/40.json","tag":"random-seed-4"},{"id":402747,"solverName":"random-seed-4-17","problemId":40,"score":322959670,"solutionPath":"solutions/random-seed-4-17/40.json","tag":"random-seed-4"},{"id":398985,"solverName":"random-seed-4-14","problemId":40,"score":322959600,"solutionPath":"solutions/random-seed-4-14/40.json","tag":"random-seed-4"},{"id":395007,"solverName":"random-seed-4-10","problemId":40,"score":322959440,"solutionPath":"solutions/random-seed-4-10/40.json","tag":"random-seed-4"},{"id":405799,"solverName":"random-seed-4-19","problemId":41,"score":159751670,"solutionPath":"solutions/random-seed-4-19/41.json","tag":"random-seed-4"},{"id":403851,"solverName":"random-seed-4-18","problemId":41,"score":159698000,"solutionPath":"solutions/random-seed-4-18/41.json","tag":"random-seed-4"},{"id":402748,"solverName":"random-seed-4-17","problemId":41,"score":159697990,"solutionPath":"solutions/random-seed-4-17/41.json","tag":"random-seed-4"},{"id":400126,"solverName":"random-seed-4-15","problemId":41,"score":159697980,"solutionPath":"solutions/random-seed-4-15/41.json","tag":"random-seed-4"},{"id":398986,"solverName":"random-seed-4-14","problemId":41,"score":159697430,"solutionPath":"solutions/random-seed-4-14/41.json","tag":"random-seed-4"},{"id":405800,"solverName":"random-seed-4-19","problemId":42,"score":69771870,"solutionPath":"solutions/random-seed-4-19/42.json","tag":"random-seed-4"},{"id":400127,"solverName":"random-seed-4-15","problemId":42,"score":69769280,"solutionPath":"solutions/random-seed-4-15/42.json","tag":"random-seed-4"},{"id":393062,"solverName":"random-seed-4-8","problemId":42,"score":69757260,"solutionPath":"solutions/random-seed-4-8/42.json","tag":"random-seed-4"},{"id":391646,"solverName":"random-seed-4-6","problemId":42,"score":69755970,"solutionPath":"solutions/random-seed-4-6/42.json","tag":"random-seed-4"},{"id":390405,"solverName":"random-seed-4-4","problemId":42,"score":69755960,"solutionPath":"solutions/random-seed-4-4/42.json","tag":"random-seed-4"},{"id":405801,"solverName":"random-seed-4-19","problemId":43,"score":16107020,"solutionPath":"solutions/random-seed-4-19/43.json","tag":"random-seed-4"},{"id":402750,"solverName":"random-seed-4-17","problemId":43,"score":16106590,"solutionPath":"solutions/random-seed-4-17/43.json","tag":"random-seed-4"},{"id":401396,"solverName":"random-seed-4-16","problemId":43,"score":16106580,"solutionPath":"solutions/random-seed-4-16/43.json","tag":"random-seed-4"},{"id":400128,"solverName":"random-seed-4-15","problemId":43,"score":16106230,"solutionPath":"solutions/random-seed-4-15/43.json","tag":"random-seed-4"},{"id":393063,"solverName":"random-seed-4-8","problemId":43,"score":16105990,"solutionPath":"solutions/random-seed-4-8/43.json","tag":"random-seed-4"},{"id":405802,"solverName":"random-seed-4-19","problemId":44,"score":404186630,"solutionPath":"solutions/random-seed-4-19/44.json","tag":"random-seed-4"},{"id":403854,"solverName":"random-seed-4-18","problemId":44,"score":404180250,"solutionPath":"solutions/random-seed-4-18/44.json","tag":"random-seed-4"},{"id":402751,"solverName":"random-seed-4-17","problemId":44,"score":404180210,"solutionPath":"solutions/random-seed-4-17/44.json","tag":"random-seed-4"},{"id":393064,"solverName":"random-seed-4-8","problemId":44,"score":404179530,"solutionPath":"solutions/random-seed-4-8/44.json","tag":"random-seed-4"},{"id":392355,"solverName":"random-seed-4-7","problemId":44,"score":400492280,"solutionPath":"solutions/random-seed-4-7/44.json","tag":"random-seed-4"},{"id":405803,"solverName":"random-seed-4-19","problemId":45,"score":189544300,"solutionPath":"solutions/random-seed-4-19/45.json","tag":"random-seed-4"},{"id":403855,"solverName":"random-seed-4-18","problemId":45,"score":189542840,"solutionPath":"solutions/random-seed-4-18/45.json","tag":"random-seed-4"},{"id":402752,"solverName":"random-seed-4-17","problemId":45,"score":189542570,"solutionPath":"solutions/random-seed-4-17/45.json","tag":"random-seed-4"},{"id":401398,"solverName":"random-seed-4-16","problemId":45,"score":189534720,"solutionPath":"solutions/random-seed-4-16/45.json","tag":"random-seed-4"},{"id":400130,"solverName":"random-seed-4-15","problemId":45,"score":189526560,"solutionPath":"solutions/random-seed-4-15/45.json","tag":"random-seed-4"},{"id":405804,"solverName":"random-seed-4-19","problemId":46,"score":48400360,"solutionPath":"solutions/random-seed-4-19/46.json","tag":"random-seed-4"},{"id":403856,"solverName":"random-seed-4-18","problemId":46,"score":48398540,"solutionPath":"solutions/random-seed-4-18/46.json","tag":"random-seed-4"},{"id":402753,"solverName":"random-seed-4-17","problemId":46,"score":48398530,"solutionPath":"solutions/random-seed-4-17/46.json","tag":"random-seed-4"},{"id":398991,"solverName":"random-seed-4-14","problemId":46,"score":48398510,"solutionPath":"solutions/random-seed-4-14/46.json","tag":"random-seed-4"},{"id":395013,"solverName":"random-seed-4-10","problemId":46,"score":48398490,"solutionPath":"solutions/random-seed-4-10/46.json","tag":"random-seed-4"},{"id":407042,"solverName":"random-seed-4-20","problemId":47,"score":18515090,"solutionPath":"solutions/random-seed-4-20/47.json","tag":"random-seed-4"},{"id":405805,"solverName":"random-seed-4-19","problemId":47,"score":18515070,"solutionPath":"solutions/random-seed-4-19/47.json","tag":"random-seed-4"},{"id":403857,"solverName":"random-seed-4-18","problemId":47,"score":18509890,"solutionPath":"solutions/random-seed-4-18/47.json","tag":"random-seed-4"},{"id":402754,"solverName":"random-seed-4-17","problemId":47,"score":18509480,"solutionPath":"solutions/random-seed-4-17/47.json","tag":"random-seed-4"},{"id":398992,"solverName":"random-seed-4-14","problemId":47,"score":18509300,"solutionPath":"solutions/random-seed-4-14/47.json","tag":"random-seed-4"},{"id":405806,"solverName":"random-seed-4-19","problemId":48,"score":138987920,"solutionPath":"solutions/random-seed-4-19/48.json","tag":"random-seed-4"},{"id":403858,"solverName":"random-seed-4-18","problemId":48,"score":138980910,"solutionPath":"solutions/random-seed-4-18/48.json","tag":"random-seed-4"},{"id":401401,"solverName":"random-seed-4-16","problemId":48,"score":138980270,"solutionPath":"solutions/random-seed-4-16/48.json","tag":"random-seed-4"},{"id":400133,"solverName":"random-seed-4-15","problemId":48,"score":138980230,"solutionPath":"solutions/random-seed-4-15/48.json","tag":"random-seed-4"},{"id":398993,"solverName":"random-seed-4-14","problemId":48,"score":138980170,"solutionPath":"solutions/random-seed-4-14/48.json","tag":"random-seed-4"},{"id":405807,"solverName":"random-seed-4-19","problemId":49,"score":50640860,"solutionPath":"solutions/random-seed-4-19/49.json","tag":"random-seed-4"},{"id":403859,"solverName":"random-seed-4-18","problemId":49,"score":50633600,"solutionPath":"solutions/random-seed-4-18/49.json","tag":"random-seed-4"},{"id":400134,"solverName":"random-seed-4-15","problemId":49,"score":50633440,"solutionPath":"solutions/random-seed-4-15/49.json","tag":"random-seed-4"},{"id":398994,"solverName":"random-seed-4-14","problemId":49,"score":50633330,"solutionPath":"solutions/random-seed-4-14/49.json","tag":"random-seed-4"},{"id":397050,"solverName":"random-seed-4-12","problemId":49,"score":50633010,"solutionPath":"solutions/random-seed-4-12/49.json","tag":"random-seed-4"},{"id":407045,"solverName":"random-seed-4-20","problemId":50,"score":116028590,"solutionPath":"solutions/random-seed-4-20/50.json","tag":"random-seed-4"},{"id":405808,"solverName":"random-seed-4-19","problemId":50,"score":116028490,"solutionPath":"solutions/random-seed-4-19/50.json","tag":"random-seed-4"},{"id":403860,"solverName":"random-seed-4-18","problemId":50,"score":116020880,"solutionPath":"solutions/random-seed-4-18/50.json","tag":"random-seed-4"},{"id":402757,"solverName":"random-seed-4-17","problemId":50,"score":116019900,"solutionPath":"solutions/random-seed-4-17/50.json","tag":"random-seed-4"},{"id":401403,"solverName":"random-seed-4-16","problemId":50,"score":115988310,"solutionPath":"solutions/random-seed-4-16/50.json","tag":"random-seed-4"},{"id":403861,"solverName":"random-seed-4-18","problemId":51,"score":42144820,"solutionPath":"solutions/random-seed-4-18/51.json","tag":"random-seed-4"},{"id":402758,"solverName":"random-seed-4-17","problemId":51,"score":42144810,"solutionPath":"solutions/random-seed-4-17/51.json","tag":"random-seed-4"},{"id":400136,"solverName":"random-seed-4-15","problemId":51,"score":42138020,"solutionPath":"solutions/random-seed-4-15/51.json","tag":"random-seed-4"},{"id":393071,"solverName":"random-seed-4-8","problemId":51,"score":42136710,"solutionPath":"solutions/random-seed-4-8/51.json","tag":"random-seed-4"},{"id":392362,"solverName":"random-seed-4-7","problemId":51,"score":42132540,"solutionPath":"solutions/random-seed-4-7/51.json","tag":"random-seed-4"},{"id":407047,"solverName":"random-seed-4-20","problemId":52,"score":78787670,"solutionPath":"solutions/random-seed-4-20/52.json","tag":"random-seed-4"},{"id":405810,"solverName":"random-seed-4-19","problemId":52,"score":78787660,"solutionPath":"solutions/random-seed-4-19/52.json","tag":"random-seed-4"},{"id":403862,"solverName":"random-seed-4-18","problemId":52,"score":78780380,"solutionPath":"solutions/random-seed-4-18/52.json","tag":"random-seed-4"},{"id":402759,"solverName":"random-seed-4-17","problemId":52,"score":78777820,"solutionPath":"solutions/random-seed-4-17/52.json","tag":"random-seed-4"},{"id":398997,"solverName":"random-seed-4-14","problemId":52,"score":78777810,"solutionPath":"solutions/random-seed-4-14/52.json","tag":"random-seed-4"},{"id":407048,"solverName":"random-seed-4-20","problemId":53,"score":223034530,"solutionPath":"solutions/random-seed-4-20/53.json","tag":"random-seed-4"},{"id":405811,"solverName":"random-seed-4-19","problemId":53,"score":223034450,"solutionPath":"solutions/random-seed-4-19/53.json","tag":"random-seed-4"},{"id":403863,"solverName":"random-seed-4-18","problemId":53,"score":223023560,"solutionPath":"solutions/random-seed-4-18/53.json","tag":"random-seed-4"},{"id":402760,"solverName":"random-seed-4-17","problemId":53,"score":223020500,"solutionPath":"solutions/random-seed-4-17/53.json","tag":"random-seed-4"},{"id":400138,"solverName":"random-seed-4-15","problemId":53,"score":223019350,"solutionPath":"solutions/random-seed-4-15/53.json","tag":"random-seed-4"},{"id":405812,"solverName":"random-seed-4-19","problemId":54,"score":36761670,"solutionPath":"solutions/random-seed-4-19/54.json","tag":"random-seed-4"},{"id":403864,"solverName":"random-seed-4-18","problemId":54,"score":36758500,"solutionPath":"solutions/random-seed-4-18/54.json","tag":"random-seed-4"},{"id":398999,"solverName":"random-seed-4-14","problemId":54,"score":36757580,"solutionPath":"solutions/random-seed-4-14/54.json","tag":"random-seed-4"},{"id":398026,"solverName":"random-seed-4-13","problemId":54,"score":36756450,"solutionPath":"solutions/random-seed-4-13/54.json","tag":"random-seed-4"},{"id":397055,"solverName":"random-seed-4-12","problemId":54,"score":36756410,"solutionPath":"solutions/random-seed-4-12/54.json","tag":"random-seed-4"},{"id":405813,"solverName":"random-seed-4-19","problemId":55,"score":8777140,"solutionPath":"solutions/random-seed-4-19/55.json","tag":"random-seed-4"},{"id":393075,"solverName":"random-seed-4-8","problemId":55,"score":8777130,"solutionPath":"solutions/random-seed-4-8/55.json","tag":"random-seed-4"},{"id":389009,"solverName":"random-seed-4-2","problemId":55,"score":8776920,"solutionPath":"solutions/random-seed-4-2/55.json","tag":"random-seed-4"},{"id":388218,"solverName":"random-seed-4-1","problemId":55,"score":8776880,"solutionPath":"solutions/random-seed-4-1/55.json","tag":"random-seed-4"},{"id":407051,"solverName":"random-seed-4-20","problemId":56,"score":1033382709,"solutionPath":"solutions/random-seed-4-20/56.json","tag":"random-seed-4"},{"id":405814,"solverName":"random-seed-4-19","problemId":56,"score":1033382195,"solutionPath":"solutions/random-seed-4-19/56.json","tag":"random-seed-4"},{"id":403866,"solverName":"random-seed-4-18","problemId":56,"score":1033369313,"solutionPath":"solutions/random-seed-4-18/56.json","tag":"random-seed-4"},{"id":402763,"solverName":"random-seed-4-17","problemId":56,"score":1033179977,"solutionPath":"solutions/random-seed-4-17/56.json","tag":"random-seed-4"},{"id":400141,"solverName":"random-seed-4-15","problemId":56,"score":1033062407,"solutionPath":"solutions/random-seed-4-15/56.json","tag":"random-seed-4"},{"id":407052,"solverName":"random-seed-4-20","problemId":57,"score":1381840671,"solutionPath":"solutions/random-seed-4-20/57.json","tag":"random-seed-4"},{"id":405815,"solverName":"random-seed-4-19","problemId":57,"score":1381817598,"solutionPath":"solutions/random-seed-4-19/57.json","tag":"random-seed-4"},{"id":403867,"solverName":"random-seed-4-18","problemId":57,"score":1381803739,"solutionPath":"solutions/random-seed-4-18/57.json","tag":"random-seed-4"},{"id":402764,"solverName":"random-seed-4-17","problemId":57,"score":1381787109,"solutionPath":"solutions/random-seed-4-17/57.json","tag":"random-seed-4"},{"id":401410,"solverName":"random-seed-4-16","problemId":57,"score":1381698640,"solutionPath":"solutions/random-seed-4-16/57.json","tag":"random-seed-4"},{"id":407053,"solverName":"random-seed-4-20","problemId":58,"score":565252706,"solutionPath":"solutions/random-seed-4-20/58.json","tag":"random-seed-4"},{"id":405816,"solverName":"random-seed-4-19","problemId":58,"score":565237885,"solutionPath":"solutions/random-seed-4-19/58.json","tag":"random-seed-4"},{"id":403868,"solverName":"random-seed-4-18","problemId":58,"score":565237872,"solutionPath":"solutions/random-seed-4-18/58.json","tag":"random-seed-4"},{"id":402765,"solverName":"random-seed-4-17","problemId":58,"score":564796989,"solutionPath":"solutions/random-seed-4-17/58.json","tag":"random-seed-4"},{"id":401411,"solverName":"random-seed-4-16","problemId":58,"score":563582183,"solutionPath":"solutions/random-seed-4-16/58.json","tag":"random-seed-4"},{"id":407054,"solverName":"random-seed-4-20","problemId":59,"score":389241677,"solutionPath":"solutions/random-seed-4-20/59.json","tag":"random-seed-4"},{"id":405817,"solverName":"random-seed-4-19","problemId":59,"score":389239259,"solutionPath":"solutions/random-seed-4-19/59.json","tag":"random-seed-4"},{"id":403869,"solverName":"random-seed-4-18","problemId":59,"score":389044670,"solutionPath":"solutions/random-seed-4-18/59.json","tag":"random-seed-4"},{"id":402766,"solverName":"random-seed-4-17","problemId":59,"score":388857128,"solutionPath":"solutions/random-seed-4-17/59.json","tag":"random-seed-4"},{"id":399004,"solverName":"random-seed-4-14","problemId":59,"score":385575774,"solutionPath":"solutions/random-seed-4-14/59.json","tag":"random-seed-4"},{"id":407055,"solverName":"random-seed-4-20","problemId":60,"score":50570085,"solutionPath":"solutions/random-seed-4-20/60.json","tag":"random-seed-4"},{"id":405818,"solverName":"random-seed-4-19","problemId":60,"score":50569785,"solutionPath":"solutions/random-seed-4-19/60.json","tag":"random-seed-4"},{"id":403870,"solverName":"random-seed-4-18","problemId":60,"score":50546956,"solutionPath":"solutions/random-seed-4-18/60.json","tag":"random-seed-4"},{"id":402767,"solverName":"random-seed-4-17","problemId":60,"score":50544163,"solutionPath":"solutions/random-seed-4-17/60.json","tag":"random-seed-4"},{"id":399005,"solverName":"random-seed-4-14","problemId":60,"score":50541466,"solutionPath":"solutions/random-seed-4-14/60.json","tag":"random-seed-4"},{"id":407056,"solverName":"random-seed-4-20","problemId":61,"score":748876432,"solutionPath":"solutions/random-seed-4-20/61.json","tag":"random-seed-4"},{"id":405819,"solverName":"random-seed-4-19","problemId":61,"score":748736891,"solutionPath":"solutions/random-seed-4-19/61.json","tag":"random-seed-4"},{"id":403871,"solverName":"random-seed-4-18","problemId":61,"score":743299462,"solutionPath":"solutions/random-seed-4-18/61.json","tag":"random-seed-4"},{"id":402768,"solverName":"random-seed-4-17","problemId":61,"score":740326989,"solutionPath":"solutions/random-seed-4-17/61.json","tag":"random-seed-4"},{"id":401414,"solverName":"random-seed-4-16","problemId":61,"score":740279783,"solutionPath":"solutions/random-seed-4-16/61.json","tag":"random-seed-4"},{"id":407057,"solverName":"random-seed-4-20","problemId":62,"score":555614355,"solutionPath":"solutions/random-seed-4-20/62.json","tag":"random-seed-4"},{"id":405820,"solverName":"random-seed-4-19","problemId":62,"score":555582105,"solutionPath":"solutions/random-seed-4-19/62.json","tag":"random-seed-4"},{"id":403872,"solverName":"random-seed-4-18","problemId":62,"score":553789653,"solutionPath":"solutions/random-seed-4-18/62.json","tag":"random-seed-4"},{"id":402769,"solverName":"random-seed-4-17","problemId":62,"score":553132555,"solutionPath":"solutions/random-seed-4-17/62.json","tag":"random-seed-4"},{"id":401415,"solverName":"random-seed-4-16","problemId":62,"score":552664579,"solutionPath":"solutions/random-seed-4-16/62.json","tag":"random-seed-4"},{"id":407058,"solverName":"random-seed-4-20","problemId":63,"score":1579465119,"solutionPath":"solutions/random-seed-4-20/63.json","tag":"random-seed-4"},{"id":405821,"solverName":"random-seed-4-19","problemId":63,"score":1579407721,"solutionPath":"solutions/random-seed-4-19/63.json","tag":"random-seed-4"},{"id":403873,"solverName":"random-seed-4-18","problemId":63,"score":1578715217,"solutionPath":"solutions/random-seed-4-18/63.json","tag":"random-seed-4"},{"id":402770,"solverName":"random-seed-4-17","problemId":63,"score":1577588716,"solutionPath":"solutions/random-seed-4-17/63.json","tag":"random-seed-4"},{"id":400148,"solverName":"random-seed-4-15","problemId":63,"score":1574416080,"solutionPath":"solutions/random-seed-4-15/63.json","tag":"random-seed-4"},{"id":407059,"solverName":"random-seed-4-20","problemId":64,"score":1510256331,"solutionPath":"solutions/random-seed-4-20/64.json","tag":"random-seed-4"},{"id":405822,"solverName":"random-seed-4-19","problemId":64,"score":1510222253,"solutionPath":"solutions/random-seed-4-19/64.json","tag":"random-seed-4"},{"id":403874,"solverName":"random-seed-4-18","problemId":64,"score":1506038728,"solutionPath":"solutions/random-seed-4-18/64.json","tag":"random-seed-4"},{"id":402771,"solverName":"random-seed-4-17","problemId":64,"score":1503491639,"solutionPath":"solutions/random-seed-4-17/64.json","tag":"random-seed-4"},{"id":401417,"solverName":"random-seed-4-16","problemId":64,"score":1502953441,"solutionPath":"solutions/random-seed-4-16/64.json","tag":"random-seed-4"},{"id":407060,"solverName":"random-seed-4-20","problemId":65,"score":729992733,"solutionPath":"solutions/random-seed-4-20/65.json","tag":"random-seed-4"},{"id":405823,"solverName":"random-seed-4-19","problemId":65,"score":729992674,"solutionPath":"solutions/random-seed-4-19/65.json","tag":"random-seed-4"},{"id":403875,"solverName":"random-seed-4-18","problemId":65,"score":729991828,"solutionPath":"solutions/random-seed-4-18/65.json","tag":"random-seed-4"},{"id":402772,"solverName":"random-seed-4-17","problemId":65,"score":729984665,"solutionPath":"solutions/random-seed-4-17/65.json","tag":"random-seed-4"},{"id":401418,"solverName":"random-seed-4-16","problemId":65,"score":729983909,"solutionPath":"solutions/random-seed-4-16/65.json","tag":"random-seed-4"},{"id":407061,"solverName":"random-seed-4-20","problemId":66,"score":1013438040,"solutionPath":"solutions/random-seed-4-20/66.json","tag":"random-seed-4"},{"id":405824,"solverName":"random-seed-4-19","problemId":66,"score":1012766536,"solutionPath":"solutions/random-seed-4-19/66.json","tag":"random-seed-4"},{"id":403876,"solverName":"random-seed-4-18","problemId":66,"score":1011391976,"solutionPath":"solutions/random-seed-4-18/66.json","tag":"random-seed-4"},{"id":402773,"solverName":"random-seed-4-17","problemId":66,"score":1010927006,"solutionPath":"solutions/random-seed-4-17/66.json","tag":"random-seed-4"},{"id":401419,"solverName":"random-seed-4-16","problemId":66,"score":1010774716,"solutionPath":"solutions/random-seed-4-16/66.json","tag":"random-seed-4"},{"id":407062,"solverName":"random-seed-4-20","problemId":67,"score":3142020728,"solutionPath":"solutions/random-seed-4-20/67.json","tag":"random-seed-4"},{"id":405825,"solverName":"random-seed-4-19","problemId":67,"score":3141769909,"solutionPath":"solutions/random-seed-4-19/67.json","tag":"random-seed-4"},{"id":403877,"solverName":"random-seed-4-18","problemId":67,"score":3141769355,"solutionPath":"solutions/random-seed-4-18/67.json","tag":"random-seed-4"},{"id":402774,"solverName":"random-seed-4-17","problemId":67,"score":3135692591,"solutionPath":"solutions/random-seed-4-17/67.json","tag":"random-seed-4"},{"id":401420,"solverName":"random-seed-4-16","problemId":67,"score":3135686874,"solutionPath":"solutions/random-seed-4-16/67.json","tag":"random-seed-4"},{"id":407063,"solverName":"random-seed-4-20","problemId":68,"score":2585006580,"solutionPath":"solutions/random-seed-4-20/68.json","tag":"random-seed-4"},{"id":405826,"solverName":"random-seed-4-19","problemId":68,"score":2584241265,"solutionPath":"solutions/random-seed-4-19/68.json","tag":"random-seed-4"},{"id":403878,"solverName":"random-seed-4-18","problemId":68,"score":2577844659,"solutionPath":"solutions/random-seed-4-18/68.json","tag":"random-seed-4"},{"id":402775,"solverName":"random-seed-4-17","problemId":68,"score":2574619857,"solutionPath":"solutions/random-seed-4-17/68.json","tag":"random-seed-4"},{"id":401421,"solverName":"random-seed-4-16","problemId":68,"score":2574602774,"solutionPath":"solutions/random-seed-4-16/68.json","tag":"random-seed-4"},{"id":407064,"solverName":"random-seed-4-20","problemId":69,"score":2513616921,"solutionPath":"solutions/random-seed-4-20/69.json","tag":"random-seed-4"},{"id":405827,"solverName":"random-seed-4-19","problemId":69,"score":2513112965,"solutionPath":"solutions/random-seed-4-19/69.json","tag":"random-seed-4"},{"id":403879,"solverName":"random-seed-4-18","problemId":69,"score":2512851996,"solutionPath":"solutions/random-seed-4-18/69.json","tag":"random-seed-4"},{"id":402776,"solverName":"random-seed-4-17","problemId":69,"score":2511980308,"solutionPath":"solutions/random-seed-4-17/69.json","tag":"random-seed-4"},{"id":401422,"solverName":"random-seed-4-16","problemId":69,"score":2511939062,"solutionPath":"solutions/random-seed-4-16/69.json","tag":"random-seed-4"},{"id":407065,"solverName":"random-seed-4-20","problemId":70,"score":397618751,"solutionPath":"solutions/random-seed-4-20/70.json","tag":"random-seed-4"},{"id":405828,"solverName":"random-seed-4-19","problemId":70,"score":397617413,"solutionPath":"solutions/random-seed-4-19/70.json","tag":"random-seed-4"},{"id":403880,"solverName":"random-seed-4-18","problemId":70,"score":396499203,"solutionPath":"solutions/random-seed-4-18/70.json","tag":"random-seed-4"},{"id":402777,"solverName":"random-seed-4-17","problemId":70,"score":396126316,"solutionPath":"solutions/random-seed-4-17/70.json","tag":"random-seed-4"},{"id":401423,"solverName":"random-seed-4-16","problemId":70,"score":396094650,"solutionPath":"solutions/random-seed-4-16/70.json","tag":"random-seed-4"},{"id":407066,"solverName":"random-seed-4-20","problemId":71,"score":2105793005,"solutionPath":"solutions/random-seed-4-20/71.json","tag":"random-seed-4"},{"id":403881,"solverName":"random-seed-4-18","problemId":71,"score":2105782813,"solutionPath":"solutions/random-seed-4-18/71.json","tag":"random-seed-4"},{"id":402778,"solverName":"random-seed-4-17","problemId":71,"score":2105480518,"solutionPath":"solutions/random-seed-4-17/71.json","tag":"random-seed-4"},{"id":401424,"solverName":"random-seed-4-16","problemId":71,"score":2105441018,"solutionPath":"solutions/random-seed-4-16/71.json","tag":"random-seed-4"},{"id":400156,"solverName":"random-seed-4-15","problemId":71,"score":2104882781,"solutionPath":"solutions/random-seed-4-15/71.json","tag":"random-seed-4"},{"id":407067,"solverName":"random-seed-4-20","problemId":72,"score":1446083483,"solutionPath":"solutions/random-seed-4-20/72.json","tag":"random-seed-4"},{"id":403882,"solverName":"random-seed-4-18","problemId":72,"score":1446042964,"solutionPath":"solutions/random-seed-4-18/72.json","tag":"random-seed-4"},{"id":402779,"solverName":"random-seed-4-17","problemId":72,"score":1444424845,"solutionPath":"solutions/random-seed-4-17/72.json","tag":"random-seed-4"},{"id":401425,"solverName":"random-seed-4-16","problemId":72,"score":1444323756,"solutionPath":"solutions/random-seed-4-16/72.json","tag":"random-seed-4"},{"id":400157,"solverName":"random-seed-4-15","problemId":72,"score":1444264101,"solutionPath":"solutions/random-seed-4-15/72.json","tag":"random-seed-4"},{"id":407068,"solverName":"random-seed-4-20","problemId":73,"score":445821454,"solutionPath":"solutions/random-seed-4-20/73.json","tag":"random-seed-4"},{"id":405831,"solverName":"random-seed-4-19","problemId":73,"score":445819961,"solutionPath":"solutions/random-seed-4-19/73.json","tag":"random-seed-4"},{"id":403883,"solverName":"random-seed-4-18","problemId":73,"score":445819659,"solutionPath":"solutions/random-seed-4-18/73.json","tag":"random-seed-4"},{"id":401426,"solverName":"random-seed-4-16","problemId":73,"score":445800949,"solutionPath":"solutions/random-seed-4-16/73.json","tag":"random-seed-4"},{"id":400158,"solverName":"random-seed-4-15","problemId":73,"score":445800929,"solutionPath":"solutions/random-seed-4-15/73.json","tag":"random-seed-4"},{"id":407069,"solverName":"random-seed-4-20","problemId":74,"score":984830187,"solutionPath":"solutions/random-seed-4-20/74.json","tag":"random-seed-4"},{"id":405832,"solverName":"random-seed-4-19","problemId":74,"score":984750040,"solutionPath":"solutions/random-seed-4-19/74.json","tag":"random-seed-4"},{"id":403884,"solverName":"random-seed-4-18","problemId":74,"score":984741068,"solutionPath":"solutions/random-seed-4-18/74.json","tag":"random-seed-4"},{"id":402781,"solverName":"random-seed-4-17","problemId":74,"score":984372987,"solutionPath":"solutions/random-seed-4-17/74.json","tag":"random-seed-4"},{"id":401427,"solverName":"random-seed-4-16","problemId":74,"score":984358736,"solutionPath":"solutions/random-seed-4-16/74.json","tag":"random-seed-4"},{"id":407070,"solverName":"random-seed-4-20","problemId":75,"score":137798905,"solutionPath":"solutions/random-seed-4-20/75.json","tag":"random-seed-4"},{"id":405833,"solverName":"random-seed-4-19","problemId":75,"score":137755325,"solutionPath":"solutions/random-seed-4-19/75.json","tag":"random-seed-4"},{"id":403885,"solverName":"random-seed-4-18","problemId":75,"score":137729521,"solutionPath":"solutions/random-seed-4-18/75.json","tag":"random-seed-4"},{"id":402782,"solverName":"random-seed-4-17","problemId":75,"score":137686343,"solutionPath":"solutions/random-seed-4-17/75.json","tag":"random-seed-4"},{"id":400160,"solverName":"random-seed-4-15","problemId":75,"score":137685673,"solutionPath":"solutions/random-seed-4-15/75.json","tag":"random-seed-4"},{"id":407071,"solverName":"random-seed-4-20","problemId":76,"score":890721988,"solutionPath":"solutions/random-seed-4-20/76.json","tag":"random-seed-4"},{"id":405834,"solverName":"random-seed-4-19","problemId":76,"score":890718122,"solutionPath":"solutions/random-seed-4-19/76.json","tag":"random-seed-4"},{"id":403886,"solverName":"random-seed-4-18","problemId":76,"score":890717023,"solutionPath":"solutions/random-seed-4-18/76.json","tag":"random-seed-4"},{"id":402783,"solverName":"random-seed-4-17","problemId":76,"score":890532926,"solutionPath":"solutions/random-seed-4-17/76.json","tag":"random-seed-4"},{"id":401429,"solverName":"random-seed-4-16","problemId":76,"score":890475733,"solutionPath":"solutions/random-seed-4-16/76.json","tag":"random-seed-4"},{"id":407072,"solverName":"random-seed-4-20","problemId":77,"score":766520628,"solutionPath":"solutions/random-seed-4-20/77.json","tag":"random-seed-4"},{"id":405835,"solverName":"random-seed-4-19","problemId":77,"score":766344616,"solutionPath":"solutions/random-seed-4-19/77.json","tag":"random-seed-4"},{"id":403887,"solverName":"random-seed-4-18","problemId":77,"score":766344612,"solutionPath":"solutions/random-seed-4-18/77.json","tag":"random-seed-4"},{"id":402784,"solverName":"random-seed-4-17","problemId":77,"score":766244764,"solutionPath":"solutions/random-seed-4-17/77.json","tag":"random-seed-4"},{"id":401430,"solverName":"random-seed-4-16","problemId":77,"score":766244651,"solutionPath":"solutions/random-seed-4-16/77.json","tag":"random-seed-4"},{"id":407073,"solverName":"random-seed-4-20","problemId":78,"score":1153600634,"solutionPath":"solutions/random-seed-4-20/78.json","tag":"random-seed-4"},{"id":405836,"solverName":"random-seed-4-19","problemId":78,"score":1153463300,"solutionPath":"solutions/random-seed-4-19/78.json","tag":"random-seed-4"},{"id":403888,"solverName":"random-seed-4-18","problemId":78,"score":1153454078,"solutionPath":"solutions/random-seed-4-18/78.json","tag":"random-seed-4"},{"id":402785,"solverName":"random-seed-4-17","problemId":78,"score":1153156989,"solutionPath":"solutions/random-seed-4-17/78.json","tag":"random-seed-4"},{"id":401431,"solverName":"random-seed-4-16","problemId":78,"score":1153025907,"solutionPath":"solutions/random-seed-4-16/78.json","tag":"random-seed-4"},{"id":407074,"solverName":"random-seed-4-20","problemId":79,"score":519619206,"solutionPath":"solutions/random-seed-4-20/79.json","tag":"random-seed-4"},{"id":405837,"solverName":"random-seed-4-19","problemId":79,"score":519347262,"solutionPath":"solutions/random-seed-4-19/79.json","tag":"random-seed-4"},{"id":403889,"solverName":"random-seed-4-18","problemId":79,"score":518865197,"solutionPath":"solutions/random-seed-4-18/79.json","tag":"random-seed-4"},{"id":402786,"solverName":"random-seed-4-17","problemId":79,"score":517733973,"solutionPath":"solutions/random-seed-4-17/79.json","tag":"random-seed-4"},{"id":401432,"solverName":"random-seed-4-16","problemId":79,"score":517474709,"solutionPath":"solutions/random-seed-4-16/79.json","tag":"random-seed-4"},{"id":407075,"solverName":"random-seed-4-20","problemId":80,"score":1272964735,"solutionPath":"solutions/random-seed-4-20/80.json","tag":"random-seed-4"},{"id":403890,"solverName":"random-seed-4-18","problemId":80,"score":1272964228,"solutionPath":"solutions/random-seed-4-18/80.json","tag":"random-seed-4"},{"id":402787,"solverName":"random-seed-4-17","problemId":80,"score":1272951505,"solutionPath":"solutions/random-seed-4-17/80.json","tag":"random-seed-4"},{"id":401433,"solverName":"random-seed-4-16","problemId":80,"score":1272951132,"solutionPath":"solutions/random-seed-4-16/80.json","tag":"random-seed-4"},{"id":400165,"solverName":"random-seed-4-15","problemId":80,"score":1272951028,"solutionPath":"solutions/random-seed-4-15/80.json","tag":"random-seed-4"},{"id":407076,"solverName":"random-seed-4-20","problemId":81,"score":338614578,"solutionPath":"solutions/random-seed-4-20/81.json","tag":"random-seed-4"},{"id":405839,"solverName":"random-seed-4-19","problemId":81,"score":338587608,"solutionPath":"solutions/random-seed-4-19/81.json","tag":"random-seed-4"},{"id":403891,"solverName":"random-seed-4-18","problemId":81,"score":338574635,"solutionPath":"solutions/random-seed-4-18/81.json","tag":"random-seed-4"},{"id":402788,"solverName":"random-seed-4-17","problemId":81,"score":338354695,"solutionPath":"solutions/random-seed-4-17/81.json","tag":"random-seed-4"},{"id":401434,"solverName":"random-seed-4-16","problemId":81,"score":337226346,"solutionPath":"solutions/random-seed-4-16/81.json","tag":"random-seed-4"},{"id":407077,"solverName":"random-seed-4-20","problemId":82,"score":256387198,"solutionPath":"solutions/random-seed-4-20/82.json","tag":"random-seed-4"},{"id":403892,"solverName":"random-seed-4-18","problemId":82,"score":256354150,"solutionPath":"solutions/random-seed-4-18/82.json","tag":"random-seed-4"},{"id":402789,"solverName":"random-seed-4-17","problemId":82,"score":256344236,"solutionPath":"solutions/random-seed-4-17/82.json","tag":"random-seed-4"},{"id":400167,"solverName":"random-seed-4-15","problemId":82,"score":256342136,"solutionPath":"solutions/random-seed-4-15/82.json","tag":"random-seed-4"},{"id":399027,"solverName":"random-seed-4-14","problemId":82,"score":256205994,"solutionPath":"solutions/random-seed-4-14/82.json","tag":"random-seed-4"},{"id":407078,"solverName":"random-seed-4-20","problemId":83,"score":569636674,"solutionPath":"solutions/random-seed-4-20/83.json","tag":"random-seed-4"},{"id":405841,"solverName":"random-seed-4-19","problemId":83,"score":569632300,"solutionPath":"solutions/random-seed-4-19/83.json","tag":"random-seed-4"},{"id":403893,"solverName":"random-seed-4-18","problemId":83,"score":569628784,"solutionPath":"solutions/random-seed-4-18/83.json","tag":"random-seed-4"},{"id":402790,"solverName":"random-seed-4-17","problemId":83,"score":569554890,"solutionPath":"solutions/random-seed-4-17/83.json","tag":"random-seed-4"},{"id":401436,"solverName":"random-seed-4-16","problemId":83,"score":569547325,"solutionPath":"solutions/random-seed-4-16/83.json","tag":"random-seed-4"},{"id":407079,"solverName":"random-seed-4-20","problemId":84,"score":797506417,"solutionPath":"solutions/random-seed-4-20/84.json","tag":"random-seed-4"},{"id":403894,"solverName":"random-seed-4-18","problemId":84,"score":797500036,"solutionPath":"solutions/random-seed-4-18/84.json","tag":"random-seed-4"},{"id":400169,"solverName":"random-seed-4-15","problemId":84,"score":797492751,"solutionPath":"solutions/random-seed-4-15/84.json","tag":"random-seed-4"},{"id":399029,"solverName":"random-seed-4-14","problemId":84,"score":797475829,"solutionPath":"solutions/random-seed-4-14/84.json","tag":"random-seed-4"},{"id":397085,"solverName":"random-seed-4-12","problemId":84,"score":797322740,"solutionPath":"solutions/random-seed-4-12/84.json","tag":"random-seed-4"},{"id":407080,"solverName":"random-seed-4-20","problemId":85,"score":568606964,"solutionPath":"solutions/random-seed-4-20/85.json","tag":"random-seed-4"},{"id":403895,"solverName":"random-seed-4-18","problemId":85,"score":568606898,"solutionPath":"solutions/random-seed-4-18/85.json","tag":"random-seed-4"},{"id":400170,"solverName":"random-seed-4-15","problemId":85,"score":568606608,"solutionPath":"solutions/random-seed-4-15/85.json","tag":"random-seed-4"},{"id":399030,"solverName":"random-seed-4-14","problemId":85,"score":568605597,"solutionPath":"solutions/random-seed-4-14/85.json","tag":"random-seed-4"},{"id":397086,"solverName":"random-seed-4-12","problemId":85,"score":568592076,"solutionPath":"solutions/random-seed-4-12/85.json","tag":"random-seed-4"},{"id":407081,"solverName":"random-seed-4-20","problemId":86,"score":346101074,"solutionPath":"solutions/random-seed-4-20/86.json","tag":"random-seed-4"},{"id":405844,"solverName":"random-seed-4-19","problemId":86,"score":346055018,"solutionPath":"solutions/random-seed-4-19/86.json","tag":"random-seed-4"},{"id":403896,"solverName":"random-seed-4-18","problemId":86,"score":343640799,"solutionPath":"solutions/random-seed-4-18/86.json","tag":"random-seed-4"},{"id":402793,"solverName":"random-seed-4-17","problemId":86,"score":343577596,"solutionPath":"solutions/random-seed-4-17/86.json","tag":"random-seed-4"},{"id":401439,"solverName":"random-seed-4-16","problemId":86,"score":343577567,"solutionPath":"solutions/random-seed-4-16/86.json","tag":"random-seed-4"},{"id":407082,"solverName":"random-seed-4-20","problemId":87,"score":236695766,"solutionPath":"solutions/random-seed-4-20/87.json","tag":"random-seed-4"},{"id":405845,"solverName":"random-seed-4-19","problemId":87,"score":236695400,"solutionPath":"solutions/random-seed-4-19/87.json","tag":"random-seed-4"},{"id":403897,"solverName":"random-seed-4-18","problemId":87,"score":236694996,"solutionPath":"solutions/random-seed-4-18/87.json","tag":"random-seed-4"},{"id":402794,"solverName":"random-seed-4-17","problemId":87,"score":236529079,"solutionPath":"solutions/random-seed-4-17/87.json","tag":"random-seed-4"},{"id":401440,"solverName":"random-seed-4-16","problemId":87,"score":236503528,"solutionPath":"solutions/random-seed-4-16/87.json","tag":"random-seed-4"},{"id":405846,"solverName":"random-seed-4-19","problemId":88,"score":1281724798,"solutionPath":"solutions/random-seed-4-19/88.json","tag":"random-seed-4"},{"id":403898,"solverName":"random-seed-4-18","problemId":88,"score":1281338728,"solutionPath":"solutions/random-seed-4-18/88.json","tag":"random-seed-4"},{"id":402795,"solverName":"random-seed-4-17","problemId":88,"score":1281306576,"solutionPath":"solutions/random-seed-4-17/88.json","tag":"random-seed-4"},{"id":400173,"solverName":"random-seed-4-15","problemId":88,"score":1281286382,"solutionPath":"solutions/random-seed-4-15/88.json","tag":"random-seed-4"},{"id":399033,"solverName":"random-seed-4-14","problemId":88,"score":1281125476,"solutionPath":"solutions/random-seed-4-14/88.json","tag":"random-seed-4"},{"id":407084,"solverName":"random-seed-4-20","problemId":89,"score":267453987,"solutionPath":"solutions/random-seed-4-20/89.json","tag":"random-seed-4"},{"id":405847,"solverName":"random-seed-4-19","problemId":89,"score":267453652,"solutionPath":"solutions/random-seed-4-19/89.json","tag":"random-seed-4"},{"id":403899,"solverName":"random-seed-4-18","problemId":89,"score":267452635,"solutionPath":"solutions/random-seed-4-18/89.json","tag":"random-seed-4"},{"id":402796,"solverName":"random-seed-4-17","problemId":89,"score":267449532,"solutionPath":"solutions/random-seed-4-17/89.json","tag":"random-seed-4"},{"id":400174,"solverName":"random-seed-4-15","problemId":89,"score":267449527,"solutionPath":"solutions/random-seed-4-15/89.json","tag":"random-seed-4"},{"id":407085,"solverName":"random-seed-4-20","problemId":90,"score":1147702563,"solutionPath":"solutions/random-seed-4-20/90.json","tag":"random-seed-4"},{"id":405848,"solverName":"random-seed-4-19","problemId":90,"score":1147686233,"solutionPath":"solutions/random-seed-4-19/90.json","tag":"random-seed-4"},{"id":403900,"solverName":"random-seed-4-18","problemId":90,"score":1147665892,"solutionPath":"solutions/random-seed-4-18/90.json","tag":"random-seed-4"},{"id":402797,"solverName":"random-seed-4-17","problemId":90,"score":1147461485,"solutionPath":"solutions/random-seed-4-17/90.json","tag":"random-seed-4"},{"id":401443,"solverName":"random-seed-4-16","problemId":90,"score":1147459373,"solutionPath":"solutions/random-seed-4-16/90.json","tag":"random-seed-4"}]}